{
  "update_time": "2026/01/20 05:36:16",
  "stations": {
    "58361": {
      "name": "闵行",
      "color": "rgb(54, 162, 235)"
    },
    "58362": {
      "name": "宝山",
      "color": "rgb(75, 192, 192)"
    },
    "58363": {
      "name": "长江口",
      "color": "rgb(153, 102, 255)"
    },
    "58365": {
      "name": "嘉定",
      "color": "rgb(255, 159, 64)"
    },
    "58366": {
      "name": "崇明",
      "color": "rgb(255, 205, 86)"
    },
    "58367": {
      "name": "徐家汇",
      "color": "rgb(255, 99, 132)"
    },
    "58369": {
      "name": "南汇",
      "color": "rgb(201, 203, 207)"
    },
    "58370": {
      "name": "浦东",
      "color": "rgb(100, 181, 246)"
    },
    "58460": {
      "name": "金山",
      "color": "rgb(239, 83, 80)"
    },
    "58461": {
      "name": "青浦",
      "color": "rgb(171, 71, 188)"
    },
    "58462": {
      "name": "松江",
      "color": "rgb(255, 112, 67)"
    },
    "58463": {
      "name": "奉贤",
      "color": "rgb(38, 198, 218)"
    },
    "58474": {
      "name": "小洋山",
      "color": "rgb(102, 187, 106)"
    }
  },
  "data": {
    "58361": [
      {
        "timestamp": "2026-01-20 05:35:57",
        "temperature": 1.9,
        "humidity": 74,
        "wind_speed": 3.2,
        "wind_dir": "东北",
        "rainfall": null,
        "pressure": 1029.7,
        "visibility": 4815
      }
    ],
    "58362": [
      {
        "timestamp": "2026-01-20 05:35:58",
        "temperature": 0.4,
        "humidity": 84,
        "wind_speed": 4.2,
        "wind_dir": "西北",
        "rainfall": 0,
        "pressure": 1029.8,
        "visibility": 18218
      }
    ],
    "58363": [
      {
        "timestamp": "2026-01-20 05:36:00",
        "temperature": 1.7,
        "humidity": 84,
        "wind_speed": 13.7,
        "wind_dir": "西北",
        "rainfall": 0,
        "pressure": 1027.3,
        "visibility": 5530
      }
    ],
    "58365": [
      {
        "timestamp": "2026-01-20 05:36:01",
        "temperature": 0.4,
        "humidity": 82,
        "wind_speed": 3.2,
        "wind_dir": "东北",
        "rainfall": 0,
        "pressure": 1030.1,
        "visibility": 14030
      }
    ],
    "58366": [
      {
        "timestamp": "2026-01-20 05:36:03",
        "temperature": 0.5,
        "humidity": 87,
        "wind_speed": 3.6,
        "wind_dir": "西北",
        "rainfall": 0,
        "pressure": 1030.3,
        "visibility": 12737
      }
    ],
    "58367": [
      {
        "timestamp": "2026-01-20 05:36:05",
        "temperature": 1.9,
        "humidity": 76,
        "wind_speed": 1.6,
        "wind_dir": "西南",
        "rainfall": 0,
        "pressure": 1029.9,
        "visibility": 18519
      }
    ],
    "58369": [
      {
        "timestamp": "2026-01-20 05:36:06",
        "temperature": 2.3,
        "humidity": 65,
        "wind_speed": 7.3,
        "wind_dir": "西北",
        "rainfall": 0,
        "pressure": 1029.2,
        "visibility": 23531
      }
    ],
    "58370": [
      {
        "timestamp": "2026-01-20 05:36:07",
        "temperature": 1.7,
        "humidity": 79,
        "wind_speed": 2.9,
        "wind_dir": "东北",
        "rainfall": 0,
        "pressure": 1029.7,
        "visibility": 15178
      }
    ],
    "58460": [
      {
        "timestamp": "2026-01-20 05:36:09",
        "temperature": 2,
        "humidity": 73,
        "wind_speed": 2.3,
        "wind_dir": "西北",
        "rainfall": 0,
        "pressure": 1029.6,
        "visibility": 20408
      }
    ],
    "58461": [
      {
        "timestamp": "2026-01-20 05:36:10",
        "temperature": 0.7,
        "humidity": 83,
        "wind_speed": 3.4,
        "wind_dir": "东北",
        "rainfall": 0,
        "pressure": 1030.2,
        "visibility": 17023
      }
    ],
    "58462": [
      {
        "timestamp": "2026-01-20 05:36:12",
        "temperature": 1.4,
        "humidity": 78,
        "wind_speed": 7,
        "wind_dir": "西北",
        "rainfall": 0,
        "pressure": 1029.6,
        "visibility": 15580
      }
    ],
    "58463": [
      {
        "timestamp": "2026-01-20 05:36:13",
        "temperature": 2.3,
        "humidity": 65,
        "wind_speed": 5.1,
        "wind_dir": "东北",
        "rainfall": 0,
        "pressure": 1029.6,
        "visibility": 29573
      }
    ],
    "58474": [
      {
        "timestamp": "2026-01-20 05:36:15",
        "temperature": 3.4,
        "humidity": 72,
        "wind_speed": 14.6,
        "wind_dir": "东北",
        "rainfall": 0,
        "pressure": 1021.4,
        "visibility": 29826
      }
    ]
  }
}