{
  "update_time": "2026/01/18 23:23:31",
  "stations": {
    "58361": {
      "name": "闵行",
      "color": "rgb(54, 162, 235)"
    },
    "58362": {
      "name": "宝山",
      "color": "rgb(75, 192, 192)"
    },
    "58363": {
      "name": "长江口",
      "color": "rgb(153, 102, 255)"
    },
    "58365": {
      "name": "嘉定",
      "color": "rgb(255, 159, 64)"
    },
    "58366": {
      "name": "崇明",
      "color": "rgb(255, 205, 86)"
    },
    "58367": {
      "name": "徐家汇",
      "color": "rgb(255, 99, 132)"
    },
    "58369": {
      "name": "南汇",
      "color": "rgb(201, 203, 207)"
    },
    "58370": {
      "name": "浦东",
      "color": "rgb(100, 181, 246)"
    },
    "58460": {
      "name": "金山",
      "color": "rgb(239, 83, 80)"
    },
    "58461": {
      "name": "青浦",
      "color": "rgb(171, 71, 188)"
    },
    "58462": {
      "name": "松江",
      "color": "rgb(255, 112, 67)"
    },
    "58463": {
      "name": "奉贤",
      "color": "rgb(38, 198, 218)"
    },
    "58474": {
      "name": "小洋山",
      "color": "rgb(102, 187, 106)"
    }
  },
  "data": {
    "58361": [
      {
        "timestamp": "2026-01-18 23:23:13",
        "temperature": 11.8,
        "humidity": 82,
        "wind_speed": 3.8,
        "wind_dir": "东北",
        "rainfall": 0,
        "pressure": 1020.7,
        "visibility": 6562
      }
    ],
    "58362": [
      {
        "timestamp": "2026-01-18 23:23:14",
        "temperature": 10.1,
        "humidity": 83,
        "wind_speed": 4.5,
        "wind_dir": "东北",
        "rainfall": 0,
        "pressure": 1020.8,
        "visibility": 13992
      }
    ],
    "58363": [
      {
        "timestamp": "2026-01-18 23:23:16",
        "temperature": 9.7,
        "humidity": 92,
        "wind_speed": 7.5,
        "wind_dir": "东北",
        "rainfall": 0,
        "pressure": 1019.4,
        "visibility": 7929
      }
    ],
    "58365": [
      {
        "timestamp": "2026-01-18 23:23:17",
        "temperature": 10.1,
        "humidity": 82,
        "wind_speed": 4.4,
        "wind_dir": "东北",
        "rainfall": 0,
        "pressure": 1021.1,
        "visibility": 7997
      }
    ],
    "58366": [
      {
        "timestamp": "2026-01-18 23:23:19",
        "temperature": 9.6,
        "humidity": 86,
        "wind_speed": 2.5,
        "wind_dir": "东北",
        "rainfall": 0,
        "pressure": 1021.6,
        "visibility": 13826
      }
    ],
    "58367": [
      {
        "timestamp": "2026-01-18 23:23:20",
        "temperature": 11.4,
        "humidity": 82,
        "wind_speed": 1.4,
        "wind_dir": "东南",
        "rainfall": 0,
        "pressure": 1021,
        "visibility": 7330
      }
    ],
    "58369": [
      {
        "timestamp": "2026-01-18 23:23:22",
        "temperature": 10.4,
        "humidity": 97,
        "wind_speed": 3.9,
        "wind_dir": "东北",
        "rainfall": 0,
        "pressure": 1020.9,
        "visibility": 8463
      }
    ],
    "58370": [
      {
        "timestamp": "2026-01-18 23:23:23",
        "temperature": 10.7,
        "humidity": 85,
        "wind_speed": 2.1,
        "wind_dir": "东北",
        "rainfall": 0,
        "pressure": 1021.1,
        "visibility": 9123
      }
    ],
    "58460": [
      {
        "timestamp": "2026-01-18 23:23:24",
        "temperature": 12.2,
        "humidity": 85,
        "wind_speed": 3.2,
        "wind_dir": "东北",
        "rainfall": 0,
        "pressure": 1020.4,
        "visibility": 6875
      }
    ],
    "58461": [
      {
        "timestamp": "2026-01-18 23:23:26",
        "temperature": 11.2,
        "humidity": 82,
        "wind_speed": 4.4,
        "wind_dir": "东北",
        "rainfall": 0,
        "pressure": 1020.9,
        "visibility": 8429
      }
    ],
    "58462": [
      {
        "timestamp": "2026-01-18 23:23:27",
        "temperature": 11.7,
        "humidity": 81,
        "wind_speed": 5.5,
        "wind_dir": "东北",
        "rainfall": 0,
        "pressure": 1020.3,
        "visibility": 8141
      }
    ],
    "58463": [
      {
        "timestamp": "2026-01-18 23:23:29",
        "temperature": 11.2,
        "humidity": 84,
        "wind_speed": 3.3,
        "wind_dir": "东北",
        "rainfall": 0,
        "pressure": 1020.7,
        "visibility": 6911
      }
    ],
    "58474": [
      {
        "timestamp": "2026-01-18 23:23:30",
        "temperature": 10.6,
        "humidity": 96,
        "wind_speed": 7,
        "wind_dir": "东北",
        "rainfall": 0,
        "pressure": 1013.6,
        "visibility": 7761
      }
    ]
  }
}